gb.py
gb_generate.py
setup.py
gifbook.egg-info/PKG-INFO
gifbook.egg-info/SOURCES.txt
gifbook.egg-info/dependency_links.txt
gifbook.egg-info/entry_points.txt
gifbook.egg-info/requires.txt
gifbook.egg-info/top_level.txt