Metadata-Version: 1.1
Name: gifbook
Version: 0.0.1
Summary: GifBook: Create sequenced Gifs from video clips and subtitles
Home-page: https://github.com/beshrkayali/gifbook/
Author: Besh Kayali
Author-email: beshrkayali@gmail.com
License: GNU GPLv3
Platform: UNKNOWN
Classifier: Environment :: Console
Classifier: License :: OSI Approved :: GNU General Public License (GPL)
